hedgehog/__init__.py
hedgehog/flasher/__init__.py
hedgehog/flasher/flasher_serial.py
hedgehog_hwc_flasher-0.1.1.dist-info/DESCRIPTION.rst
hedgehog_hwc_flasher-0.1.1.dist-info/METADATA
hedgehog_hwc_flasher-0.1.1.dist-info/RECORD
hedgehog_hwc_flasher-0.1.1.dist-info/WHEEL
hedgehog_hwc_flasher-0.1.1.dist-info/entry_points.txt
hedgehog_hwc_flasher-0.1.1.dist-info/metadata.json
hedgehog_hwc_flasher-0.1.1.dist-info/top_level.txt
